astdiff/__init__.py
astdiff/astdiff.py
astdiff-0.2.5.dist-info/entry_points.txt
astdiff-0.2.5.dist-info/LICENSE
astdiff-0.2.5.dist-info/WHEEL
astdiff-0.2.5.dist-info/METADATA
astdiff-0.2.5.dist-info/RECORD
